LICENSE
README.md
setup.cfg
setup.py
packt/__init__.py
packt/api.py
packt/claimer.py
packt/configuration.py
packt/constants.py
packt/downloader.py
packt/packtPublishingFreeEbook.py
packt/utils/__init__.py
packt/utils/anticaptcha.py
packt/utils/google_drive.py
packt/utils/mail.py
packt_ll.egg-info/PKG-INFO
packt_ll.egg-info/SOURCES.txt
packt_ll.egg-info/dependency_links.txt
packt_ll.egg-info/entry_points.txt
packt_ll.egg-info/requires.txt
packt_ll.egg-info/top_level.txt