Metadata-Version: 2.2
Name: packt-ll
Version: 1.8.4
Summary: Script for grabbing daily Packt Free Learning ebooks
Home-page: https://gitlab.com/laurentlemercier/packt-cli
Download-URL: https://gitlab.com/laurentlemercier/packt-cli/-/archive/v1.8.4/packt-cli-v1.8.4.tar.gz
Author: Łukasz Uszko / Laurent Lemercier
Author-email: laurent.lemercier@gmail.com
License: MIT
Classifier: Programming Language :: Python :: 3.8
Classifier: Programming Language :: Python :: 3.9
Classifier: Programming Language :: Python :: 3.10
Classifier: Programming Language :: Python :: 3.11
License-File: LICENSE
Requires-Dist: click==8.1.3
Requires-Dist: google-api-python-client==2.57.0
Requires-Dist: oauth2client==4.1.3
Requires-Dist: requests==2.28.1
Requires-Dist: python-slugify==6.1.2
Provides-Extra: dev
Requires-Dist: bumpversion==0.6.0; extra == "dev"
Requires-Dist: mccabe==0.7.0; extra == "dev"
Requires-Dist: pycodestyle==2.9.1; extra == "dev"
Requires-Dist: pyflakes==2.5.0; extra == "dev"
Requires-Dist: pylama==8.4.1; extra == "dev"
Dynamic: author
Dynamic: author-email
Dynamic: classifier
Dynamic: description
Dynamic: description-content-type
Dynamic: download-url
Dynamic: home-page
Dynamic: license
Dynamic: provides-extra
Dynamic: requires-dist
Dynamic: summary
